adaptive/__init__.py
adaptive/_types.py
adaptive/_version.py
adaptive/notebook_integration.py
adaptive/runner.py
adaptive/types.py
adaptive/utils.py
adaptive/learner/__init__.py
adaptive/learner/average_learner.py
adaptive/learner/average_learner1D.py
adaptive/learner/balancing_learner.py
adaptive/learner/base_learner.py
adaptive/learner/data_saver.py
adaptive/learner/integrator_coeffs.py
adaptive/learner/integrator_learner.py
adaptive/learner/learner1D.py
adaptive/learner/learner2D.py
adaptive/learner/learnerND.py
adaptive/learner/sequence_learner.py
adaptive/learner/triangulation.py
adaptive/tests/__init__.py
adaptive/tests/algorithm_4.py
adaptive/tests/test_average_learner.py
adaptive/tests/test_average_learner1d.py
adaptive/tests/test_balancing_learner.py
adaptive/tests/test_cquad.py
adaptive/tests/test_learner1d.py
adaptive/tests/test_learnernd.py
adaptive/tests/test_learners.py
adaptive/tests/test_notebook_integration.py
adaptive/tests/test_pickling.py
adaptive/tests/test_runner.py
adaptive/tests/test_sequence_learner.py
adaptive/tests/test_triangulation.py
adaptive/tests/unit/__init__.py
adaptive/tests/unit/test_learnernd.py
adaptive/tests/unit/test_learnernd_integration.py
adaptive/tests/unit/test_triangulation.py
adaptive-1.4.2.dist-info/AUTHORS.md
adaptive-1.4.2.dist-info/LICENSE
adaptive-1.4.2.dist-info/METADATA
adaptive-1.4.2.dist-info/WHEEL
adaptive-1.4.2.dist-info/top_level.txt
adaptive-1.4.2.dist-info/RECORD
