Metadata-Version: 2.1
Name: adaptive
Version: 1.4.2
Summary: Parallel active learning of mathematical functions
Maintainer: Adaptive authors
License: BSD
Project-URL: homepage, https://adaptive.readthedocs.io/
Project-URL: documentation, https://adaptive.readthedocs.io/
Project-URL: repository, https://github.com/python-adaptive/adaptive
Classifier: Development Status :: 4 - Beta
Classifier: License :: OSI Approved :: BSD License
Classifier: Intended Audience :: Science/Research
Classifier: Programming Language :: Python :: 3.11
Classifier: Programming Language :: Python :: 3.12
Classifier: Programming Language :: Python :: 3.13
Classifier: Programming Language :: Python :: 3.14
Requires-Python: >=3.11
License-File: LICENSE
License-File: AUTHORS.md
Requires-Dist: scipy
Requires-Dist: sortedcollections>=1.1
Requires-Dist: sortedcontainers>=2.0
Requires-Dist: cloudpickle
Requires-Dist: loky>=2.9
Requires-Dist: versioningit
Provides-Extra: dev
Requires-Dist: adaptive[notebook,nox,other,test]; extra == "dev"
Provides-Extra: notebook
Requires-Dist: ipython; extra == "notebook"
Requires-Dist: ipykernel>=4.8.0; extra == "notebook"
Requires-Dist: jupyter-client>=5.2.2; extra == "notebook"
Requires-Dist: holoviews>=1.9.1; extra == "notebook"
Requires-Dist: ipywidgets; extra == "notebook"
Requires-Dist: bokeh; extra == "notebook"
Requires-Dist: pandas; extra == "notebook"
Requires-Dist: matplotlib; extra == "notebook"
Requires-Dist: plotly; extra == "notebook"
Provides-Extra: other
Requires-Dist: dill; extra == "other"
Requires-Dist: distributed; extra == "other"
Requires-Dist: ipyparallel>=6.2.5; extra == "other"
Requires-Dist: pexpect; os_name != "nt" and extra == "other"
Requires-Dist: wexpect; os_name == "nt" and extra == "other"
Provides-Extra: test
Requires-Dist: flaky; extra == "test"
Requires-Dist: pytest; extra == "test"
Requires-Dist: pytest-cov; extra == "test"
Requires-Dist: pytest-randomly; extra == "test"
Requires-Dist: pytest-timeout; extra == "test"
Requires-Dist: pytest-xdist; extra == "test"
Requires-Dist: pre-commit; extra == "test"
Requires-Dist: typeguard; extra == "test"
Requires-Dist: coverage; extra == "test"
